fyers_api/__init__.py
fyers_api/accessToken.py
fyers_api/config.py
fyers_api/fyersFormation.py
fyers_api/fyersModel.py
fyers_api/fyersService.py
fyers_api-1.0.9.dist-info/DESCRIPTION.rst
fyers_api-1.0.9.dist-info/METADATA
fyers_api-1.0.9.dist-info/RECORD
fyers_api-1.0.9.dist-info/WHEEL
fyers_api-1.0.9.dist-info/metadata.json
fyers_api-1.0.9.dist-info/top_level.txt
